airfoilpy/__init__.py
airfoilpy-1.1.2.dist-info/METADATA
airfoilpy-1.1.2.dist-info/WHEEL
airfoilpy-1.1.2.dist-info/top_level.txt
airfoilpy-1.1.2.dist-info/RECORD
