Metadata-Version: 2.1
Name: airfoilpy
Version: 1.1.2
Summary: A basic package for generating and working with airfoil shapes.
Author: Josh
Author-email: your.email@example.com
Classifier: Programming Language :: Python :: 3
Classifier: License :: OSI Approved :: MIT License
Classifier: Operating System :: OS Independent
Requires-Python: >=3.7
Requires-Dist: numpy
